modules/__init__.py
modules/vcftoabook.py
vcftoabook/__init__.py
vcftoabook/cli.py
vcftoabook/functions.py
vcftoabook/parser.py
vcftoabook/vcftoabook.py
vcftoabook-0.4.4.dist-info/METADATA
vcftoabook-0.4.4.dist-info/WHEEL
vcftoabook-0.4.4.dist-info/entry_points.txt
vcftoabook-0.4.4.dist-info/top_level.txt
vcftoabook-0.4.4.dist-info/RECORD
