Metadata-Version: 2.1
Name: vcftoabook
Version: 0.4.4
Summary: A cli tool for converting vcf files to abook
Home-page: https://github.com/trev-dev/vcftoabook
Author: Trevor Richards
Author-email: trev@trevdev.ca
License: UNKNOWN
Platform: UNKNOWN
Classifier: Development Status :: 4 - Beta
Classifier: Environment :: Console
Classifier: Programming Language :: Python :: 3
Classifier: License :: OSI Approved :: GNU General Public License v3 (GPLv3)
Classifier: Operating System :: OS Independent
Classifier: Topic :: Communications :: Email :: Address Book
Requires-Python: >=3.6
